{"info":{"_postman_id":"34848d49-aeef-4be0-b209-43bfc79172a9","name":"repo1Doc","schema":"https://schema.getpostman.com/json/collection/v2.1.0/collection.json"},"item":[{"name":"Sample endpoint: Returns details about a particular user","id":"4dcbe5e3-e2c4-4c95-819b-8e7feada4c4c","request":{"method":"GET","header":[],"url":{"raw":"{{baseUrl}}/user?id=-85345678","host":["{{baseUrl}}"],"path":["user"],"query":[{"key":"id","value":"-85345678","description":"(Required) ID of the user"}]}},"response":[{"id":"2c6d747d-71d2-4a85-bc44-a09a8d1ae05c","name":"Sample response: Details about a user by ID","originalRequest":{"method":"GET","header":[],"url":{"raw":"{{baseUrl}}/user?id=-85345678","host":["{{baseUrl}}"],"path":["user"],"query":[{"key":"id","value":"-85345678"}]}},"status":"OK","code":200,"_postman_previewlanguage":"json","header":[{"disabled":false,"description":"A link to the next page of responses","key":"x-next","value":"aute sunt irure"},{"key":"Content-Type","value":"application/json"}],"cookie":[],"responseTime":null,"body":"{\n \"id\": -77596423,\n \"name\": \"amet esse cillum\",\n \"tag\": \"quis sint\"\n}"},{"id":"03247d30-e41c-4d2f-b54e-5efb6881cd2a","name":"Unexpected error","originalRequest":{"method":"GET","header":[],"url":{"raw":"{{baseUrl}}/user?id=-85345678","host":["{{baseUrl}}"],"path":["user"],"query":[{"key":"id","value":"-85345678"}]}},"status":"Internal Server Error","code":500,"_postman_previewlanguage":"json","header":[{"key":"Content-Type","value":"application/json"}],"cookie":[],"responseTime":null,"body":"{\n \"code\": -26385221,\n \"message\": \"enim sed fugiat\"\n}"}]}],"variable":[{"id":"257dff2b-6332-4080-af1e-8fbac0828954","key":"baseUrl","value":"http://localhost:3000","type":"string"}]}